etc/openvpn-monitor/apache.conf.example
etc/openvpn-monitor/openvpn-monitor.conf.example
openvpn_monitor/__init__.py
openvpn_monitor/app.py
openvpn_monitor/__pycache__/__init__.cpython-312.opt-1.pyc
openvpn_monitor/__pycache__/app.cpython-312.opt-1.pyc
openvpn_monitor/config/__init__.py
openvpn_monitor/config/loader.py
openvpn_monitor/config/__pycache__/__init__.cpython-312.opt-1.pyc
openvpn_monitor/config/__pycache__/loader.cpython-312.opt-1.pyc
openvpn_monitor/location_data/__init__.py
openvpn_monitor/location_data/__pycache__/__init__.cpython-312.opt-1.pyc
openvpn_monitor/location_data/maxmind/__init__.py
openvpn_monitor/location_data/maxmind/geoip.py
openvpn_monitor/location_data/maxmind/__pycache__/__init__.cpython-312.opt-1.pyc
openvpn_monitor/location_data/maxmind/__pycache__/geoip.cpython-312.opt-1.pyc
openvpn_monitor/static/dist/.yarn-integrity
openvpn_monitor/static/dist/bootstrap3/Gruntfile.js
openvpn_monitor/static/dist/bootstrap3/LICENSE
openvpn_monitor/static/dist/bootstrap3/README.md
openvpn_monitor/static/dist/bootstrap3/package.json
openvpn_monitor/static/dist/bootstrap3/dist/css/bootstrap-theme.css
openvpn_monitor/static/dist/bootstrap3/dist/css/bootstrap-theme.css.map
openvpn_monitor/static/dist/bootstrap3/dist/css/bootstrap-theme.min.css
openvpn_monitor/static/dist/bootstrap3/dist/css/bootstrap.css
openvpn_monitor/static/dist/bootstrap3/dist/css/bootstrap.css.map
openvpn_monitor/static/dist/bootstrap3/dist/css/bootstrap.min.css
openvpn_monitor/static/dist/bootstrap3/dist/fonts/glyphicons-halflings-regular.eot
openvpn_monitor/static/dist/bootstrap3/dist/fonts/glyphicons-halflings-regular.svg
openvpn_monitor/static/dist/bootstrap3/dist/fonts/glyphicons-halflings-regular.ttf
openvpn_monitor/static/dist/bootstrap3/dist/fonts/glyphicons-halflings-regular.woff
openvpn_monitor/static/dist/bootstrap3/dist/fonts/glyphicons-halflings-regular.woff2
openvpn_monitor/static/dist/bootstrap3/dist/js/bootstrap.js
openvpn_monitor-2.0.4.dist-info/AUTHORS
openvpn_monitor-2.0.4.dist-info/COPYING
openvpn_monitor-2.0.4.dist-info/METADATA
openvpn_monitor-2.0.4.dist-info/WHEEL
openvpn_monitor-2.0.4.dist-info/top_level.txt
openvpn_monitor-2.0.4.dist-info/RECORD
