Metadata-Version: 2.1
Name: openvpn-monitor
Version: 2.0.4
Summary: A simple web based openvpn monitor
Home-page: http://openvpn-monitor.openbytes.ie
Author: Marcus Furlong
Author-email: furlongm@gmail.com
License: GPLv3
Keywords: web openvpn monitor
Classifier: Development Status :: 4 - Beta
Classifier: Environment :: Web Environment
Classifier: Topic :: Internet :: WWW/HTTP :: WSGI :: Application
Classifier: License :: OSI Approved :: GNU General Public License v3 (GPLv3)
License-File: COPYING
License-File: AUTHORS
Requires-Dist: Flask==3.1.0
Requires-Dist: Flask-WTF==1.2.2
Requires-Dist: geoip2==4.8.1
Requires-Dist: humanize==4.11.0
Requires-Dist: semver==3.0.2
